odoo/addons/purchase_force_invoiced_quantity/README.rst
odoo/addons/purchase_force_invoiced_quantity/__init__.py
odoo/addons/purchase_force_invoiced_quantity/__manifest__.py
odoo/addons/purchase_force_invoiced_quantity/demo/demo_product.xml
odoo/addons/purchase_force_invoiced_quantity/demo/demo_purchase_order.xml
odoo/addons/purchase_force_invoiced_quantity/i18n/it.po
odoo/addons/purchase_force_invoiced_quantity/i18n/pt_BR.po
odoo/addons/purchase_force_invoiced_quantity/i18n/purchase_force_invoiced_quantity.pot
odoo/addons/purchase_force_invoiced_quantity/migrations/18.0.1.1.0/pre-migration.py
odoo/addons/purchase_force_invoiced_quantity/models/__init__.py
odoo/addons/purchase_force_invoiced_quantity/models/purchase_order_line.py
odoo/addons/purchase_force_invoiced_quantity/readme/CONFIGURE.md
odoo/addons/purchase_force_invoiced_quantity/readme/CONTEXT.md
odoo/addons/purchase_force_invoiced_quantity/readme/CONTRIBUTORS.md
odoo/addons/purchase_force_invoiced_quantity/readme/DESCRIPTION.md
odoo/addons/purchase_force_invoiced_quantity/readme/USAGE.md
odoo/addons/purchase_force_invoiced_quantity/static/description/icon.png
odoo/addons/purchase_force_invoiced_quantity/static/description/index.html
odoo/addons/purchase_force_invoiced_quantity/tests/__init__.py
odoo/addons/purchase_force_invoiced_quantity/tests/test_purchase_force_invoiced_quantity.py
odoo/addons/purchase_force_invoiced_quantity/views/purchase_order.xml
odoo_addon_purchase_force_invoiced_quantity-18.0.1.1.1.2.dist-info/METADATA
odoo_addon_purchase_force_invoiced_quantity-18.0.1.1.1.2.dist-info/WHEEL
odoo_addon_purchase_force_invoiced_quantity-18.0.1.1.1.2.dist-info/top_level.txt
odoo_addon_purchase_force_invoiced_quantity-18.0.1.1.1.2.dist-info/RECORD
