Metadata-Version: 2.1
Name: odoo-addon-purchase_force_invoiced_quantity
Version: 18.0.1.1.1.2
Requires-Python: >=3.10
Requires-Dist: odoo-addon-purchase_force_invoiced==18.0.*
Requires-Dist: odoo==18.0.*
Summary: Add manual invoice quantity in purchase order lines
Home-page: https://github.com/OCA/purchase-workflow
License: AGPL-3
Author: Cetmix, Odoo Community Association (OCA)
Author-email: support@odoo-community.org
Classifier: Programming Language :: Python
Classifier: Framework :: Odoo
Classifier: Framework :: Odoo :: 18.0
Classifier: License :: OSI Approved :: GNU Affero General Public License v3
